gdauth.py
gdget.py
gdmkdir.py
gdperm.py
gdput.py
gdrm.py
setup.cfg
setup.py
gdcmdtools/__init__.py
gdcmdtools/about.py
gdcmdtools/auth.py
gdcmdtools/base.py
gdcmdtools/cp.py
gdcmdtools/find.py
gdcmdtools/get.py
gdcmdtools/ls.py
gdcmdtools/mkdir.py
gdcmdtools/perm.py
gdcmdtools/put.py
gdcmdtools/rm.py
gdcmdtools.egg-info/PKG-INFO
gdcmdtools.egg-info/SOURCES.txt
gdcmdtools.egg-info/dependency_links.txt
gdcmdtools.egg-info/requires.txt
gdcmdtools.egg-info/top_level.txt