Metadata-Version: 1.0
Name: gdcmdtools
Version: 1.07
Summary: Google drive command-line tools
Home-page: https://github.com/tienfuc/gdcmdtools
Author: ctf <tienfu.c@gmail.com>
Author-email: tienfu.c@gmail.com
License: BSD
Platform: UNKNOWN
